{
  "quit": "q",
  "quit_upper": "Q",
  "craft": "c",
  "craft_upper": "C",
  "equip": "e",
  "build": "b",
  "chest": "o",
  "chest_upper": "O",
  "look": "x",
  "dig": "d",
  "repeat": ".",
  "reload": "r",
  "reload_upper": "R",
  "save": "s",
  "load": "L",
  "move_up": "KEY_UP",
  "move_down": "KEY_DOWN",
  "move_left": "KEY_LEFT",
  "move_right": "KEY_RIGHT",
  "move_up_alt": "k",
  "move_down_alt": "j",
  "move_left_alt": "h",
  "move_right_alt": "l",
  "confirm": "KEY_ENTER",
  "switch_tab": ",",
  "transfer_all": "+",
  "legacy_shop": "p",
  "save_upper": "S",
  "inventory": "i",
  "sprint": "f"
}