[
  {
    "id": "village",
    "name": "村庄",
    "biomes": ["草原", "温带森林"],
    "rarity": 0.03,
    "min_distance": 80,
    "size": [5, 10],
    "buildings": ["小屋", "农田", "水井"],
    "population": [10, 30],
    "trades": ["食物", "木材", "工具"],
    "event_triggers": {
      "discover": {
        "message": "你发现了一个宁静的村庄。村民好奇地打量着你。",
        "actions": ["trade", "rest"]
      },
      "help": {
        "message": "村民感谢你的帮助，赠送了一些物资。",
        "reward": {"食物": 5, "药草": 3}
      }
    }
  },
  {
    "id": "camp",
    "name": "猎人营地",
    "biomes": ["针叶林", "苔原"],
    "rarity": 0.04,
    "min_distance": 100,
    "size": [2, 4],
    "buildings": ["篝火", "帐篷", "晾肉架"],
    "population": [3, 8],
    "trades": ["兽皮", "肉干", "骨器"],
    "event_triggers": {
      "discover": {
        "message": "树林深处，你找到了一个猎人营地。猎人们警惕地注视着你。",
        "actions": ["trade", "rest"]
      }
    }
  },
  {
    "id": "trading_post",
    "name": "贸易站",
    "biomes": ["草原", "沙漠", "温带森林"],
    "rarity": 0.02,
    "min_distance": 120,
    "size": [3, 6],
    "buildings": ["驿站", "仓库", "马厩"],
    "population": [5, 15],
    "trades": ["矿石", "宝石", "装备", "稀有物品"],
    "event_triggers": {
      "discover": {
        "message": "商队的旗帜在远处飘扬——你找到了一个贸易站！",
        "actions": ["trade", "repair", "quest"]
      }
    }
  },
  {
    "id": "ruins",
    "name": "遗迹",
    "biomes": ["沙漠", "雨林", "苔原"],
    "rarity": 0.025,
    "min_distance": 60,
    "size": [4, 8],
    "buildings": ["断壁", "祭坛", "地下入口"],
    "population": [0, 0],
    "trades": [],
    "event_triggers": {
      "discover": {
        "message": "残垣断壁间，你感受到古老文明的气息。也许地下藏着秘密...",
        "actions": ["explore", "loot"]
      },
      "explore": {
        "message": "你在遗迹深处发现了古老的宝藏！",
        "reward": {"金矿石": 5, "钻石原石": 1, "古代遗物": 1}
      }
    }
  },
  {
    "id": "hermit",
    "name": "隐士小屋",
    "biomes": ["针叶林", "苔原", "温带森林"],
    "rarity": 0.015,
    "min_distance": 150,
    "size": [1, 2],
    "buildings": ["小屋", "药草园"],
    "population": [1, 1],
    "trades": ["稀有药草", "知识", "附魔物品"],
    "event_triggers": {
      "discover": {
        "message": "密林深处，一位隐士在他的小屋前向你招手。",
        "actions": ["trade", "learn"]
      }
    }
  }
]
